{
  "experiment_id": "78e7745f-51c4-42ff-a421-ccb40598bcfa",
  "timestamp": "2025-11-30T15:26:25.158528",
  "workflow_features": {
    "N": 8,
    "v_mean": 12900132.875,
    "v_std": 6190763.385850457,
    "v_max": 22168046.0,
    "v_min": 5702095.0,
    "edge_count": 6,
    "edge_density": 0.10714285714285714,
    "d_mean": 4765257.904698507,
    "d_std": 4811027.509734527,
    "d_max": 11844552.205007283,
    "d_min": 535003.3294003536,
    "nodes_linear": 1,
    "nodes_source": 3,
    "nodes_sink": 3,
    "critical_path_length": 0
  },
  "environment_features": {
    "location_count": 8,
    "iot_count": 3,
    "edge_count": 2,
    "cloud_count": 3,
    "dr_mean": 0.0003190092744766382,
    "dr_std": 0.0008681915370674689,
    "dr_max": 0.0028247283139965136,
    "dr_min": 0.0,
    "de_mean": 5.7034058237889835e-05,
    "de_std": 4.877414474289733e-05,
    "vr_mean": 6.036310982196352e-08,
    "vr_std": 3.087720767354707e-08,
    "ve_mean": 3.7985315903438327e-07,
    "ve_std": 1.7062756547895125e-07,
    "regime": "network-bound"
  },
  "params": {
    "CT": 0.2,
    "CE": 1.2,
    "delta_t": 1,
    "delta_e": 1
  },
  "optimal_policy": [
    2,
    2,
    2,
    2,
    2,
    2,
    2,
    2
  ],
  "best_cost": 1321.256827,
  "evaluated_policies": 0,
  "skipped_policies": 0,
  "summary": "Workflow: 8 tasks\n  - Avg compute: 1.29e+07 cycles (std: 6.19e+06)\n  - Edge density: 10.71% (6 edges)\n  - Avg data dependency: 4.77e+06 bytes\n  - Critical path length: ~0 hops\n  - Structure: Multiple sources/sinks (parallel)\nEnvironment: 8 locations\n  - 2 edge, 3 cloud servers\n  - Avg network latency: 3.19e-04 ms/byte\n  - Avg compute speed: 6.04e-08 ms/cycle\n  - Avg task energy: 3.80e-07 mJ/cycle\n  - Regime: network-bound\nMode: BALANCED",
  "plan_excerpt": "\n## Chain-of-Thought Reasoning:\nThe Planner Agent's goal is to develop a comprehensive plan for optimizing task offloading in the given edge-cloud environment, guiding an evaluator agent to find the optimal placement policy `p`. The optimization objective is a `BALANCED` mode, meaning both time and energy costs are equally weighted (`delta_t = 1`, `delta_e = 1`).\n\n**1. Environment Analysis - Key Characteristics:**\n\n*   **Locations**: 8 locations: 3 IOT (0, 5, 7), 3 CLOUD (1, 3, 4), 2 EDGE (2, 6)"
}